{
  "description": "Citation-style coverage fixture. Each item is a realistic in-text citation as it appears after copy-paste from a manuscript. `expected` is the citation set RefCheckr SHOULD detect. `knownGap: true` marks styles we do NOT yet support — the harness reports these separately as a target, not a failure.",
  "items": [
    { "style": "vancouver-superscript-comma", "text": "teprotumumab reduced proptosis by 2.82 mm versus placebo.1,2", "expected": [1, 2], "knownGap": false },
    { "style": "vancouver-superscript-range", "text": "consistent across trials.4-6", "expected": [4, 5, 6], "knownGap": false },
    { "style": "bracketed", "text": "the ETD was -9.42 (95% CI -10.30 to -8.53) [3].", "expected": [3], "knownGap": false },
    { "style": "parenthetical-numeric", "text": "response rates were higher with active treatment (1,2).", "expected": [1, 2], "knownGap": false },
    { "style": "decimal-not-a-citation", "text": "the p-value was 0.17 and the mean was 4.13 overall.", "expected": [], "knownGap": false },
    { "style": "author-year-parenthetical", "text": "Smith et al. (2020) reported a hazard ratio of 0.80.", "expected": [], "targetExpected": ["Smith 2020"], "knownGap": true },
    { "style": "author-year-narrative", "text": "As shown by Jones and colleagues in 2019, survival improved.", "expected": [], "targetExpected": ["Jones 2019"], "knownGap": true },
    { "style": "number-adjacent-superscript", "text": "the reduction was sustained to week 24.1", "expected": [], "targetExpected": [1], "knownGap": true, "comment": "A superscript citation immediately after a number (24.1) is suppressed by the decimal guard that correctly ignores values like 0.17. Genuine ambiguity; tracked as a target." },
    { "style": "endpoint-number-not-a-citation", "text": "the ACR20 response rate was higher with active treatment", "expected": [], "knownGap": false, "comment": "Named endpoints with trailing numbers (ACR20, PASI90, EASI75) must not be read as citations." },
    { "style": "identifier-number-not-a-citation", "text": "patients with grade3 events and a CD4 count", "expected": [], "knownGap": false, "comment": "Letter-glued single numbers (grade3, CD4, type2) are identifiers, not citations." },
    { "style": "letter-glued-list-is-a-citation", "text": "these outcomes were consistent1,2 across trials", "expected": [1, 2], "knownGap": false, "comment": "A letter-glued list/range is still a strong citation signal and must convert." }
  ]
}
